Metadata-Version: 2.1
Name: upsonic-run
Version: 0.1.1
Summary: The cloud python function runner !
Home-page: https://github.com/Upsonic/Upsonic-Run
Author: Onur Atakan ULUSOY
Author-email: atadogan06@gmail.com
License: MIT
Platform: UNKNOWN
Requires-Python: >= 3
